noman/__init__.py
noman/__main__.py
noman/ansi_renderer.py
noman/colors.py
noman/viewer.py
noman/pages/__init__.py
noman/pages/en/__init__.py
noman/pages/en/apt-file.md
noman/pages/en/apt.md
noman/pages/en/awk.md
noman/pages/en/basename.md
noman/pages/en/break.md
noman/pages/en/case.md
noman/pages/en/cat.md
noman/pages/en/chgrp.md
noman/pages/en/chmod.md
noman/pages/en/chsh.md
noman/pages/en/cmp.md
noman/pages/en/continue.md
noman/pages/en/cp.md
noman/pages/en/curl.md
noman/pages/en/cut.md
noman/pages/en/date.md
noman/pages/en/dd.md
noman/pages/en/df.md
noman/pages/en/diff.md
noman/pages/en/diff3.md
noman/pages/en/dig.md
noman/pages/en/dirname.md
noman/pages/en/dmesg.md
noman/pages/en/docker-build.md
noman/pages/en/docker-compose.md
noman/pages/en/docker-run.md
noman/pages/en/docker.md
noman/pages/en/dpkg.md
noman/pages/en/du.md
noman/pages/en/echo.md
noman/pages/en/egrep.md
noman/pages/en/env.md
noman/pages/en/eval.md
noman/pages/en/expr.md
noman/pages/en/false.md
noman/pages/en/file.md
noman/pages/en/find.md
noman/pages/en/for.md
noman/pages/en/free.md
noman/pages/en/function.md
noman/pages/en/gdb.md
noman/pages/en/getent.md
noman/pages/en/getopt.md
noman/pages/en/git-add.md
noman/pages/en/git-branch.md
noman/pages/en/git-commit.md
noman/pages/en/git-merge.md
noman/pages/en/git-pull.md
noman/pages/en/git-push.md
noman/pages/en/git-rebase.md
noman/pages/en/git-reset.md
noman/pages/en/git-stash.md
noman/pages/en/git-switch.md
noman/pages/en/git.md
noman/pages/en/gpasswd.md
noman/pages/en/grep.md
noman/pages/en/groupadd.md
noman/pages/en/groupdel.md
noman/pages/en/groupmod.md
noman/pages/en/groups.md
noman/pages/en/gunzip.md
noman/pages/en/gzip.md
noman/pages/en/hd.md
noman/pages/en/head.md
noman/pages/en/host.md
noman/pages/en/hostname.md
noman/pages/en/http.md
noman/pages/en/if.md
noman/pages/en/install.md
noman/pages/en/iostat.md
noman/pages/en/iotop.md
noman/pages/en/ip.md
noman/pages/en/ipcs.md
noman/pages/en/journalctl.md
noman/pages/en/jq.md
noman_cli-0.2.0.dist-info/METADATA
noman_cli-0.2.0.dist-info/WHEEL
noman_cli-0.2.0.dist-info/entry_points.txt
noman_cli-0.2.0.dist-info/RECORD
