Metadata-Version: 2.4
Name: noman-cli
Version: 0.2.0
Summary: Man pages without the man
Requires-Python: >=3.10
Requires-Dist: mistune>=3.1.3
Requires-Dist: pygments>=2.19.1
